rated/__init__.py
rated/base.py
rated/client.py
rated/version.py
rated/ethereum/__init__.py
rated/ethereum/blocks.py
rated/ethereum/datatypes.py
rated/ethereum/enums.py
rated/ethereum/network.py
rated/ethereum/operators.py
rated/ethereum/p2p.py
rated/ethereum/slashings.py
rated/ethereum/validators.py
rated/ethereum/withdrawals.py
rated_python-0.0.2.dist-info/LICENSE.md
rated_python-0.0.2.dist-info/METADATA
rated_python-0.0.2.dist-info/WHEEL
rated_python-0.0.2.dist-info/top_level.txt
rated_python-0.0.2.dist-info/RECORD
