Metadata-Version: 2.1
Name: rated-python
Version: 0.0.2
Summary: Python Bindings for the Rated API
Author-email: Rated Labs <hi@rated.network>
Project-URL: Homepage, https://github.com/rated-network/rated-python
Project-URL: Issues, https://github.com/rated-network/rated-python/issues
Project-URL: Documentation, https://rated-network.github.io/rated-python/
Project-URL: Repository, https://github.com/rated-network/rated-python.git
Classifier: Programming Language :: Python :: 3
Classifier: License :: OSI Approved :: MIT License
Classifier: Operating System :: OS Independent
Requires-Python: >=3.8
License-File: LICENSE.md
Requires-Dist: httpx ==0.26.0
Requires-Dist: pyhumps ==3.8.0
Provides-Extra: dev
Requires-Dist: pytest ; extra == 'dev'
Requires-Dist: respx ; extra == 'dev'
Requires-Dist: ruff ; extra == 'dev'
Requires-Dist: mypy ; extra == 'dev'
Requires-Dist: coverage ; extra == 'dev'
